bifrost_httr/__init__.py
bifrost_httr/cli.py
bifrost_httr/py.typed
bifrost_httr/core/__init__.py
bifrost_httr/core/analysis.py
bifrost_httr/core/data_processing.py
bifrost_httr/core/distributions.py
bifrost_httr/core/model.py
bifrost_httr/core/statistics.py
bifrost_httr/data/report_templates.yml
bifrost_httr/models/BIFROST_HTTr_beta_logistic_batch.stan
bifrost_httr/models/__init__.py
bifrost_httr/utils/__init__.py
bifrost_httr/utils/compression.py
bifrost_httr/utils/config.py
bifrost_httr/utils/logging.py
bifrost_httr/visualization/__init__.py
bifrost_httr/visualization/data.py
bifrost_httr/visualization/report.py
bifrost_httr/visualization/template_loader.py
bifrost_httr-0.5.0.dist-info/METADATA
bifrost_httr-0.5.0.dist-info/WHEEL
bifrost_httr-0.5.0.dist-info/entry_points.txt
bifrost_httr-0.5.0.dist-info/licenses/LICENSE
bifrost_httr-0.5.0.dist-info/RECORD
