Metadata-Version: 2.4
Name: bifrost-httr
Version: 0.5.0
Summary: Pre-release version for testing purposes only
Author-email: Jonathan Manning <jonathan.manning@seqera.io>, Joe Reynolds <Joe.Reynolds@unilever.com>, Mark Liddell <Mark.Liddell@unilever.com>
License-Expression: LGPL-3.0-or-later
License-File: LICENSE
Classifier: License :: OSI Approved :: GNU Lesser General Public License v3 or later (LGPLv3+)
Requires-Python: >=3.10
Requires-Dist: click
Requires-Dist: cmdstanpy<2.0,>=1.2.0
Requires-Dist: multiqc==1.28
Requires-Dist: numpy<3.0,>=2.0.0
Requires-Dist: pandas<3.0,>=2.0.0
Requires-Dist: plotly<7.0,>=6.0.0
Requires-Dist: pyyaml>=6.0
Requires-Dist: scipy<2.0,>=1.10.0
Provides-Extra: dev
Requires-Dist: black; extra == 'dev'
Requires-Dist: mypy; extra == 'dev'
Requires-Dist: pytest; extra == 'dev'
Requires-Dist: ruff; extra == 'dev'
Provides-Extra: test
Requires-Dist: pytest-cov>=4.0.0; extra == 'test'
Requires-Dist: pytest>=7.0.0; extra == 'test'
